bronski/__init__.py
bronski/admin.py
bronski/management/__init__.py
bronski/management/commands/__init__.py
bronski/management/commands/bronski.py
bronski/models.py
bronski/runner.py
bronski-0.4.0.dist-info/WHEEL
bronski-0.4.0.dist-info/METADATA
bronski-0.4.0.dist-info/RECORD
