Metadata-Version: 2.1
Name: bronski
Version: 0.4.0
Summary: Simple, generic cron-like job runner service for Django
Home-page: https://github.com/uptick/bronski
License: MIT
Author: Curtis Maloney
Author-email: curtis@tinbrain.net
Requires-Python: >=3.6,<4.0
Classifier: Framework :: Django
Classifier: Framework :: Django :: 3.1
Classifier: License :: OSI Approved :: MIT License
Classifier: Programming Language :: Python
Classifier: Programming Language :: Python :: 3
Classifier: Programming Language :: Python :: 3.6
Classifier: Programming Language :: Python :: 3.7
Classifier: Programming Language :: Python :: 3.8
Classifier: Programming Language :: Python :: 3.9
Requires-Dist: croniter (>=0.3.31,<0.4.0)
Requires-Dist: django (>=3.1)
